CHANGELOG.md
LICENSE
MANIFEST.in
README.md
setup.py
pagan/__init__.py
pagan/generator.py
pagan/hashgrinder.py
pagan/pagan.py
pagan/pgnreader.py
pagan.egg-info/PKG-INFO
pagan.egg-info/SOURCES.txt
pagan.egg-info/dependency_links.txt
pagan.egg-info/requires.txt
pagan.egg-info/top_level.txt
pagan/pgn/AXE.pgn
pagan/pgn/BIGHAMMER.pgn
pagan/pgn/BODY.pgn
pagan/pgn/BOOTS.pgn
pagan/pgn/BUCKLER.pgn
pagan/pgn/DAGGER.pgn
pagan/pgn/FLAIL.pgn
pagan/pgn/GREATAXE.pgn
pagan/pgn/GREATMACE.pgn
pagan/pgn/GREATSWORD.pgn
pagan/pgn/HAIR.pgn
pagan/pgn/HAMMER.pgn
pagan/pgn/LONGSHIELD.pgn
pagan/pgn/MACE.pgn
pagan/pgn/MIN_SUBFIELD.pgn
pagan/pgn/ROUNDSHIELD.pgn
pagan/pgn/SHIELD.pgn
pagan/pgn/SHIELD_DECO.pgn
pagan/pgn/SUBFIELD.pgn
pagan/pgn/SWORD.pgn
pagan/pgn/TORSO.pgn
pagan/pgn/WAND.pgn