Metadata-Version: 1.1
Name: pagan
Version: 0.3.3
Summary: python avatar generator for absolute nerds
Home-page: https://github.com/daboth/pagan
Author: David Bothe
Author-email: davbothe@googlemail.com
License: GPL
Download-URL: https://github.com/daboth/pagan/tarball/0.3.3
Keywords: avatar,identicon,generator
Platform: UNKNOWN
Classifier: Programming Language :: Python
Classifier: Programming Language :: Python :: 3
Classifier: License :: OSI Approved :: GNU General Public License v2 (GPLv2)
Classifier: Operating System :: OS Independent
Classifier: Development Status :: 4 - Beta
Classifier: Intended Audience :: Developers
Classifier: Environment :: Web Environment
Classifier: Topic :: Software Development :: Libraries :: Python Modules
